heracles/__init__.py
heracles/py.typed
heracles/config/__init__.py
heracles/config/contexts.py
heracles/config/generation.py
heracles/config/reducers.py
heracles/config/rule.py
heracles/config/utils.py
heracles/lib/__init__.py
heracles/lib/core.py
heracles/lib/identity.py
heracles/ql/__init__.py
heracles/ql/annotation.py
heracles/ql/assertions.py
heracles/ql/duration.py
heracles/ql/factory.py
heracles/ql/format.py
heracles/ql/prelude.py
heracles/ql/funcs/__init__.py
heracles/ql/funcs/generated.py
heracles/ql/funcs/handwritten.py
heracles/unittest/generators.py
heracles/unittest/hermes.py
pkg/formatter.so
pkg/hermes
heracles_ql-0.2.0.dist-info/METADATA
heracles_ql-0.2.0.dist-info/WHEEL
heracles_ql-0.2.0.dist-info/RECORD
heracles_ql-0.2.0.dist-info/licenses/LICENSE
