Metadata-Version: 2.4
Name: heracles-ql
Version: 0.2.0
Summary: heralces-ql VictoriaMetrics DSL
Author-email: Hudson River Trading LLC <opensource@hudson-trading.com>
License-File: LICENSE
Requires-Python: >=3.11
Provides-Extra: config
Requires-Dist: pydantic>=2.11.7; extra == 'config'
Requires-Dist: pyyaml>=6.0.2; extra == 'config'
